[
  {
    "id": "p1",
    "title": "Classic T-Shirt",
    "price": 1999,
    "product_id": "5bfd0b66a342bcc9b5563216",
    "variant_id": 17887,
    "image": "https://images.unsplash.com/photo-1521572163474-6864f9cf17ab?w=600&h=600&fit=crop",
    "description": "Comfortable cotton t-shirt with a classic fit. Perfect for everyday wear."
  },
  {
    "id": "p2",
    "title": "Logo Sticker Pack",
    "price": 499,
    "product_id": "5bfd0b66a342bcc9b5563217",
    "variant_id": 17888,
    "image": "https://images.unsplash.com/photo-1578662996442-48f60103fc96?w=600&h=600&fit=crop",
    "description": "High-quality vinyl stickers featuring unique designs. Weather-resistant and durable."
  },
  {
    "id": "sami-tee",
    "title": "Sami.dev Premium Tee",
    "price": 4999,
    "product_id": "sami-tee-prod",
    "variant_id": 1001,
    "image": "https://imagesami.is-a.dev/sIMG_2231.jpeg",
    "images": ["https://imagesami.is-a.dev/sIMG_2231.jpeg","https://sami.is-a.dev/IMG_2230.jpeg","https://sami.is-a.dev/IMG_2229.jpeg"],
    "description": "Premium long-sleeve tee with Sami.dev branding. Made from high-quality, environmentally-friendly cotton with a vintage feel."
  }
]